bus/src/include/bus.v

`ifndef __BUS_HEADER__
`define __BUS_HEADER__			 

	`define BUS_MASTER_CH	   4	 
	`define BUS_MASTER_INDEX_W 2	

	`define BusOwnerBus		   1:0	
	`define BUS_OWNER_MASTER_0 2'h0	
	`define BUS_OWNER_MASTER_1 2'h1
	`define BUS_OWNER_MASTER_2 2'h2
	`define BUS_OWNER_MASTER_3 2'h3

	`define BUS_SLAVE_CH	   8	
	`define BUS_SLAVE_INDEX_W  3	
	`define BusSlaveIndexBus   2:0	
	`define BusSlaveIndexLoc   29:27 

	`define BUS_SLAVE_0		   0	
	`define BUS_SLAVE_1		   1	
	`define BUS_SLAVE_2		   2	
	`define BUS_SLAVE_3		   3	
	`define BUS_SLAVE_4		   4	
	`define BUS_SLAVE_5		   5	
	`define BUS_SLAVE_6		   6	 
	`define BUS_SLAVE_7		   7	 

`endif

bus/src/include/global_config.v

`ifndef __GLOBAL_CONFIG_HEADER__
	`define __GLOBAL_CONFIG_HEADER__	// インクルードガード

//------------------------------------------------------------------------------
// 設定項目
//------------------------------------------------------------------------------
	/********** ターゲットデバイス : いずれか1つを選択 **********/
//	`define TARGET_DEV_MFPGA_SPAR3E		// マルツ評価ボード
	`define TARGET_DEV_AZPR_EV_BOARD	// AZPRオリジナル評価ボード

	/********** リセット極性 : いずれか1つを選択 **********/
	// `define POSITIVE_RESET				// Active High
	`define NEGATIVE_RESET				// Active Low

	/********** メモリ制御信号の極性 : いずれか1つを選択 **********/
	`define POSITIVE_MEMORY				// Active High
//	`define NEGATIVE_MEMORY				// Active Low

	/********** I/O設定 : 実装するI/Oを定義**********/
	`define IMPLEMENT_TIMER				// タイマ
	`define IMPLEMENT_UART				// UART
	`define IMPLEMENT_GPIO				// General Purpose I/O

//------------------------------------------------------------------------------
// 設定に応じてパラメータを生成
//------------------------------------------------------------------------------
	/********** リセット極性 *********/
	// Active Low
	`ifdef POSITIVE_RESET
		`define RESET_EDGE	  posedge	// リセットエッジ
		`define RESET_ENABLE  1'b1		// リセット有効
		`define RESET_DISABLE 1'b0		// リセット無効
	`endif
	// Active High
	`ifdef NEGATIVE_RESET
		`define RESET_EDGE	  negedge	// リセットエッジ
		`define RESET_ENABLE  1'b0		// リセット有効
		`define RESET_DISABLE 1'b1		// リセット無効
	`endif

	/********** メモリ制御信号の極性 *********/
	// Actoive High
	`ifdef POSITIVE_MEMORY
		`define MEM_ENABLE	  1'b1		// メモリ有効
		`define MEM_DISABLE	  1'b0		// メモリ無効
	`endif
	// Active Low
	`ifdef NEGATIVE_MEMORY
		`define MEM_ENABLE	  1'b0		// メモリ有効
		`define MEM_DISABLE	  1'b1		// メモリ無効
	`endif

`endif

bus/src/include/stddef.v

`ifndef __STDDEF_HEADER__				
`define __STDDEF_HEADER__

	`define HIGH				1'b1	 // Highレベル
	`define LOW					1'b0	 // Lowレベル
	
	`define DISABLE				1'b0	 // 無効
	`define ENABLE				1'b1	 // 有効

	`define DISABLE_			1'b1	 // 無効
	`define ENABLE_				1'b0	 // 有効
	
	`define READ				1'b1	 // 読み出し
	`define WRITE				1'b0	 // 書き込み

	`define LSB					0		 // 最下位ビット

	`define BYTE_DATA_W			8		 // データ幅
	`define BYTE_MSB			7		 // 最上位ビット
	`define ByteDataBus			7:0		 // データバス

	`define WORD_DATA_W			32		 // データ幅
	`define WORD_MSB			31		 // 最上位ビット
	`define WordDataBus			31:0	 // データバス

	`define WORD_ADDR_W			30		 // アドレス幅
	`define WORD_ADDR_MSB		29		 // 最上位ビット
	`define WordAddrBus			29:0	 // アドレスバス

	`define BYTE_OFFSET_W		2		 // オフセット幅
	`define ByteOffsetBus		1:0		 // オフセットバス

	`define WordAddrLoc			31:2	 // ワードアドレスの位置
	`define ByteOffsetLoc		1:0		 // バイトオフセットの位置

	`define BYTE_OFFSET_WORD	2'b00	 // ワード境界

`endif

bus/src/include/nettype.v


`ifndef __NETTYPE_HEADER__	   
`define __NETTYPE_HEADER__

	`default_nettype none	   
	// `default_nettype wire	   // wire (Verilog標準)

`endif

bus/src/bus_arbiter.v

`include "nettype.v"
`include "stddef.v"
`include "global_config.v"

`include "bus.v"

module bus_arbiter (
	input  wire		   clk,		 // クロック
	input  wire		   reset,	 // 非同期リセット
	
	input  wire		   m0_req_,	 // バスリクエスト
	output reg		   m0_grnt_, // バスグラント

	input  wire		   m1_req_,	 // バスリクエスト
	output reg		   m1_grnt_, // バスグラント

	input  wire		   m2_req_,	 // バスリクエスト
	output reg		   m2_grnt_, // バスグラント

	input  wire		   m3_req_,	 // バスリクエスト
	output reg		   m3_grnt_	 // バスグラント
);

	reg [`BusOwnerBus] owner;	 // バス権の所有者
   
	always @(*) begin
		m0_grnt_ = `DISABLE_;
		m1_grnt_ = `DISABLE_;
		m2_grnt_ = `DISABLE_;
		m3_grnt_ = `DISABLE_;
		
		case (owner)
			`BUS_OWNER_MASTER_0 : begin // バスマスタ0番
				m0_grnt_ = `ENABLE_;
			end
			`BUS_OWNER_MASTER_1 : begin // バスマスタ1番
				m1_grnt_ = `ENABLE_;
			end
			`BUS_OWNER_MASTER_2 : begin // バスマスタ2番
				m2_grnt_ = `ENABLE_;
			end
			`BUS_OWNER_MASTER_3 : begin // バスマスタ3番
				m3_grnt_ = `ENABLE_;
			end
		endcase
	end
   
	always @(posedge clk or `RESET_EDGE reset) begin
		if (reset == `RESET_ENABLE) begin
			owner <= #1 `BUS_OWNER_MASTER_0;
		end else begin
			case (owner)
				`BUS_OWNER_MASTER_0 : begin
					if (m0_req_ == `ENABLE_) begin			// バスマスタ0番
						owner <= #1 `BUS_OWNER_MASTER_0;
					end else if (m1_req_ == `ENABLE_) begin // バスマスタ1番
						owner <= #1 `BUS_OWNER_MASTER_1;
					end else if (m2_req_ == `ENABLE_) begin // バスマスタ2番
						owner <= #1 `BUS_OWNER_MASTER_2;
					end else if (m3_req_ == `ENABLE_) begin // バスマスタ3番
						owner <= #1 `BUS_OWNER_MASTER_3;
					end
				end
				`BUS_OWNER_MASTER_1 : begin
					if (m1_req_ == `ENABLE_) begin			// バスマスタ1番
						owner <= #1 `BUS_OWNER_MASTER_1;
					end else if (m2_req_ == `ENABLE_) begin // バスマスタ2番
						owner <= #1 `BUS_OWNER_MASTER_2;
					end else if (m3_req_ == `ENABLE_) begin // バスマスタ3番
						owner <= #1 `BUS_OWNER_MASTER_3;
					end else if (m0_req_ == `ENABLE_) begin // バスマスタ0番
						owner <= #1 `BUS_OWNER_MASTER_0;
					end
				end
				`BUS_OWNER_MASTER_2 : begin // バス権所有者：バスマスタ2番
					if (m2_req_ == `ENABLE_) begin			// バスマスタ2番
						owner <= #1 `BUS_OWNER_MASTER_2;
					end else if (m3_req_ == `ENABLE_) begin // バスマスタ3番
						owner <= #1 `BUS_OWNER_MASTER_3;
					end else if (m0_req_ == `ENABLE_) begin // バスマスタ0番
						owner <= #1 `BUS_OWNER_MASTER_0;
					end else if (m1_req_ == `ENABLE_) begin // バスマスタ1番
						owner <= #1 `BUS_OWNER_MASTER_1;
					end
				end
				`BUS_OWNER_MASTER_3 : begin // バス権所有者：バスマスタ3番
					if (m3_req_ == `ENABLE_) begin			// バスマスタ3番
						owner <= #1 `BUS_OWNER_MASTER_3;
					end else if (m0_req_ == `ENABLE_) begin // バスマスタ0番
						owner <= #1 `BUS_OWNER_MASTER_0;
					end else if (m1_req_ == `ENABLE_) begin // バスマスタ1番
						owner <= #1 `BUS_OWNER_MASTER_1;
					end else if (m2_req_ == `ENABLE_) begin // バスマスタ2番
						owner <= #1 `BUS_OWNER_MASTER_2;
					end
				end
			endcase
		end
	end

endmodule

bus/src/bus_arbiter_tb.v
`include "bus.v"

`ifndef SIM_CYCLE
    `define SIM_CYCLE 60
`endif

// `timescale 1ns/1ns
module bus_arbiter_tb; 
    reg clk, reset; 
    reg m0_req_,m1_req_,m2_req_,m3_req_;
    wire m0_grnt_,m1_grnt_,m2_grnt_,m3_grnt_;
    parameter STEP = 5.0000; // 10 M

    bus_arbiter bus_arbiter(
        .clk(clk),
        .reset(reset),
        .m0_req_(m0_req_),
        .m0_grnt_(m0_grnt_),
        .m1_req_(m1_req_),
        .m1_grnt_(m1_grnt_),
        .m2_req_(m2_req_),
        .m2_grnt_(m2_grnt_),
        .m3_req_(m3_req_),
        .m3_grnt_(m3_grnt_));

    always #( STEP ) begin
		clk <= ~clk;
	end

    initial begin
		# 0 begin
			clk	 <= `HIGH;
			reset <= `RESET_ENABLE;
		end
        

        # ( STEP * 5 ) begin
			reset <= `RESET_DISABLE;
		end

        # ( STEP * 5 ) begin
            m0_req_ <= `ENABLE_;
        end

        # ( STEP * 6 ) begin
            m1_req_ <= `ENABLE_;
        end

        # ( STEP * 7 ) begin
            m2_req_ <= `ENABLE_;
        end

        # ( STEP * 8 ) begin
            m3_req_ <= `ENABLE_;
        end

        # ( STEP * 12 ) begin
            m0_req_ <= `DISABLE_;
        end

        # ( STEP * 14 ) begin
            m1_req_ <= `DISABLE_;
        end

        # ( STEP * 16 ) begin
            m2_req_ <= `DISABLE_;
        end

        # ( STEP * 18 ) begin
            m3_req_ <= `DISABLE_;
        end

        # ( STEP * `SIM_CYCLE ) begin
			$finish;
		end
    end

    initial
    begin            
        $dumpfile("bus_arbiter_tb.vcd"); //生成的vcd文件名称
        $dumpvars(0, bus_arbiter_tb);    //tb模块名称
    end 

endmodule

bus/build/bus_arbiter_tb.vcd
$date
	Mon Dec 25 17:34:27 2023
$end
$version
	Icarus Verilog
$end
$timescale
	1s
$end
$scope module bus_arbiter_tb $end
$var wire 1 ! m3_grnt_ $end
$var wire 1 " m2_grnt_ $end
$var wire 1 # m1_grnt_ $end
$var wire 1 $ m0_grnt_ $end
$var reg 1 % clk $end
$var reg 1 & m0_req_ $end
$var reg 1 ' m1_req_ $end
$var reg 1 ( m2_req_ $end
$var reg 1 ) m3_req_ $end
$var reg 1 * reset $end
$scope module bus_arbiter $end
$var wire 1 % clk $end
$var wire 1 & m0_req_ $end
$var wire 1 ' m1_req_ $end
$var wire 1 ( m2_req_ $end
$var wire 1 ) m3_req_ $end
$var wire 1 * reset $end
$var reg 1 $ m0_grnt_ $end
$var reg 1 # m1_grnt_ $end
$var reg 1 " m2_grnt_ $end
$var reg 1 ! m3_grnt_ $end
$var reg 2 + owner [1:0] $end
$upscope $end
$upscope $end
$enddefinitions $end
#0
$dumpvars
bx +
0*
x)
x(
x'
x&
1%
x$
x#
x"
x!
$end
#1
1!
1"
1#
0$
b0 +
#5
0%
#10
1%
#15
0%
#20
1%
#25
0%
1*
#30
1%
#35
0%
#40
1%
#45
0%
#50
1%
0&
#55
0%
#60
1%
#65
0%
#70
1%
#75
0%
#80
1%
0'
#85
0%
#90
1%
#95
0%
#100
1%
#105
0%
#110
1%
#115
0%
0(
#120
1%
#125
0%
#130
1%
#135
0%
#140
1%
#145
0%
#150
1%
#155
0%
0)
#160
1%
#165
0%
#170
1%
#175
0%
#180
1%
#185
0%
#190
1%
#195
0%
#200
1%
#205
0%
#210
1%
#215
0%
1&
#220
1%
#221
0#
1$
b1 +
#225
0%
#230
1%
#235
0%
#240
1%
#245
0%
#250
1%
#255
0%
#260
1%
#265
0%
#270
1%
#275
0%
#280
1%
#285
0%
1'
#290
1%
#291
0"
1#
b10 +
#295
0%
#300
1%
#305
0%
#310
1%
#315
0%
#320
1%
#325
0%
#330
1%
#335
0%
#340
1%
#345
0%
#350
1%
#355
0%
#360
1%
#365
0%
1(
#370
1%
#371
0!
1"
b11 +
#375
0%
#380
1%
#385
0%
#390
1%
#395
0%
#400
1%
#405
0%
#410
1%
#415
0%
#420
1%
#425
0%
#430
1%
#435
0%
#440
1%
#445
0%
#450
1%
#455
0%
1)
